AUTHORS
CHANGES.txt
INSTALL
LICENSE
MANIFEST.in
README.rst
setup.cfg
setup.py
projenv/VERSION.py
projenv/__init__.py
projenv/addprojenv2virtualenv.py
projenv/cast_value.py
projenv/common.py
projenv/expandvars.py
projenv/export_projenv.py
projenv/export_projenv.sh
projenv/main.py
projenv/mkprojenvdirs.py
projenv/mkprojenvoverride.py
projenv/mkprojenvpackage.py
projenv/projenv_template_envoverride.xml
projenv/projenv_template_envpackage.xml
projenv.egg-info/PKG-INFO
projenv.egg-info/SOURCES.txt
projenv.egg-info/dependency_links.txt
projenv.egg-info/requires.txt
projenv.egg-info/top_level.txt