Metadata-Version: 1.1
Name: projenv
Version: 2.0.5
Summary: ProjEnv allows the use of hierarchical parameter structure for projects.
Home-page: https://github.com/Acrisel/projenv
Author: Acrisel Team
Author-email: support@acrisel.com
License: MIT
Keywords: project,sandbox,virtualenv,virtualenvwrapper,configuration,parameters
Platform: UNKNOWN
Classifier: Development Status :: 5 - Production/Stable
Classifier: Environment :: Other Environment
Classifier: Intended Audience :: Developers
Classifier: License :: OSI Approved :: MIT License
Classifier: Operating System :: OS Independent
Classifier: Programming Language :: Python
Classifier: Programming Language :: Python :: 3
Classifier: Programming Language :: Python :: 3.2
Classifier: Programming Language :: Python :: 3.3
Classifier: Programming Language :: Python :: 3.4
Classifier: Programming Language :: Python :: 3.5
Classifier: Topic :: Software Development :: Libraries :: Application Frameworks
Classifier: Topic :: Software Development :: Libraries :: Python Modules
